{
  "templates": {
    "type": "JSON",
    "content": [
      {
        "id": "149895003",
        "Flight": "WS2273",
        "PickupDate": "2026-02-08",
        "PickupTime": "13:20",
        "HotelName": "Royalton Chic Antigua",
        "HotelNumber": 18628
      },
      {
        "id": "150169012",
        "Flight": "WS2273",
        "PickupDate": "2026-02-08",
        "PickupTime": "13:20",
        "HotelName": "Royalton Chic Antigua",
        "HotelNumber": 18628
      },
      {
        "id": "3BM57N",
        "Flight": "AA1359",
        "PickupDate": "2026-02-08",
        "PickupTime": "14:45",
        "HotelName": "Royalton Chic Antigua",
        "HotelNumber": 18628
      },
      {
        "id": "4586148",
        "Flight": "B6740",
        "PickupDate": "2026-02-08",
        "PickupTime": "13:00",
        "HotelName": "Royalton Chic Antigua",
        "HotelNumber": 18628
      },
      {
        "id": "4355328",
        "Flight": "AA2467",
        "PickupDate": "2026-02-08",
        "PickupTime": "11:15",
        "HotelName": "Royalton Chic Antigua",
        "HotelNumber": 18628
      },
      {
        "id": "4355824",
        "Flight": "AA2467",
        "PickupDate": "2026-02-08",
        "PickupTime": "11:15",
        "HotelName": "Royalton Chic Antigua",
        "HotelNumber": 18628
      },
      {
        "id": "7ZWDFV",
        "Flight": "WS2273",
        "PickupDate": "2026-02-08",
        "PickupTime": "13:20",
        "HotelName": "Royalton Chic Antigua",
        "HotelNumber": 18628
      },
      {
        "id": "F8PTZ5",
        "Flight": "AA2467",
        "PickupDate": "2026-02-08",
        "PickupTime": "11:15",
        "HotelName": "Royalton Chic Antigua",
        "HotelNumber": 18628
      },
      {
        "id": "NJZ3FK",
        "Flight": "X11431",
        "PickupDate": "2026-02-08",
        "PickupTime": "10:30",
        "HotelName": "Royalton Chic Antigua",
        "HotelNumber": 18628
      },
      {
        "id": "4635787",
        "Flight": "AA1359",
        "PickupDate": "2026-02-08",
        "PickupTime": "14:45",
        "HotelName": "Royalton Chic Antigua",
        "HotelNumber": 18628
      },
      {
        "id": "4571857",
        "Flight": "B6740",
        "PickupDate": "2026-02-08",
        "PickupTime": "13:00",
        "HotelName": "Royalton Chic Antigua",
        "HotelNumber": 18628
      },
      {
        "id": "147494083",
        "Flight": "WS2273",
        "PickupDate": "2026-02-08",
        "PickupTime": "13:20",
        "HotelName": "Royalton Chic Antigua",
        "HotelNumber": 18628
      }
    ],
    "source": {
      "data_source": "Google Sheets (Private)",
      "update_frequency": "Automated"
    }
  }
}